econ_jp/__init__.py
econ_jp/econ_jp.py
econ_jp/econ_kobe.py
econ_jp/econ_kyoto.py
econ_jp/econ_osaka.py
econ_jp/util.py
econ_jp-0.1.13.dist-info/LICENSE
econ_jp-0.1.13.dist-info/METADATA
econ_jp-0.1.13.dist-info/WHEEL
econ_jp-0.1.13.dist-info/top_level.txt
econ_jp-0.1.13.dist-info/RECORD
