Metadata-Version: 2.1
Name: econ-jp
Version: 0.1.13
Summary: This module returns DataFrame of
Home-page: https://github.com/chomoku/econ_jp
Author: HideyukiO
Author-email: mazarimono@gmail.com
License: MIT
Platform: UNKNOWN
Classifier: License :: OSI Approved :: MIT License
Classifier: Programming Language :: Python :: 3.10
Requires-Dist: pandas
Requires-Dist: requests
Requires-Dist: openpyxl
Requires-Dist: xlrd (>=2.0.0)
